ProgressBar/PercentProgressBar.py
ProgressBar/ProgressBar.py
ProgressBar/__init__.py
TimurkaaaaProgressBar-1.0.0.dist-info/LICENSE
TimurkaaaaProgressBar-1.0.0.dist-info/METADATA
TimurkaaaaProgressBar-1.0.0.dist-info/WHEEL
TimurkaaaaProgressBar-1.0.0.dist-info/top_level.txt
TimurkaaaaProgressBar-1.0.0.dist-info/RECORD
