Metadata-Version: 2.1
Name: TimurkaaaaProgressBar
Version: 1.0.0
Summary: a simple tool for displaying task progress in Python console applications. It allows users to see how far the process has progressed, making your code more interactive and usable.
Home-page: https://github.com/Timurkaaaaaaa/ProgressBar/
Author: Timurkaaa
Author-email: timurzarovskiy@gmail.com
Classifier: Programming Language :: Python :: 3
Classifier: License :: OSI Approved :: MIT License
Classifier: Operating System :: OS Independent
Requires-Python: >=3.6
License-File: LICENSE
